{
    "siteId": "XNAT",
    "siteUrl": "http://localhost",
    "adminEmail": "harmitage@miskatonic.edu",
    "helpContactInfo": "",
    "archivePath": "/data/xnat/archive",
    "prearchivePath": "/data/xnat/prearchive",
    "cachePath": "/data/xnat/cache",
    "buildPath": "/data/xnat/build",
    "pipelinePath": "/data/xnat/pipeline",
    "inboxPath": "/data/xnat/inbox",
    "smtpEnabled": true,
    "smtpHostname": "localhost",
    "smtpPort": 25,
    "smtpProtocol": "smtp",
    "smtpAuth": false,
    "smtpUsername": "",
    "smtpPassword": "",
    "smtpStartTls": false,
    "smtpSslTrust": "",
    "emailPrefix": "XNAT",
    "requireLogin": true,
    "userRegistration": false,
    "enableCsrfToken": true,
    "initialized": true
}